./.gitignore
./.python-version
./LICENSE
./PKG-INFO
./README.md
./README_ch.md
./__init__.py
./cli.py
./pyproject.toml
./pywen_config.json.example
./trae_config.json.example
./uv.lock
./agents/base_agent.py
./agents/qwen/loop_detection_service.py
./agents/qwen/qwen_agent.py
./agents/qwen/task_continuation_checker.py
./agents/qwen/turn.py
./agents/research/google_research_agent.py
./agents/research/research_prompts.py
./config/config.py
./config/loader.py
./core/client.py
./core/session_stats.py
./core/tool_executor.py
./core/tool_registry.py
./core/tool_scheduler.py
./core/trajectory_recorder.py
./docs/UML.md
./docs/project-structure.md
./logs/.gitkeep
./tools/__init__.py
./tools/base.py
./tools/bash_tool.py
./tools/edit_tool.py
./tools/file_tools.py
./tools/glob_tool.py
./tools/grep_tool.py
./tools/ls_tool.py
./tools/memory_tool.py
./tools/read_many_files_tool.py
./tools/web_fetch_tool.py
./tools/web_search_tool.py
./trajectories/.gitkeep
./ui/__init__.py
./ui/cli_console.py
./ui/command_processor.py
./ui/config_wizard.py
./ui/commands/__init__.py
./ui/commands/about_command.py
./ui/commands/agent_command.py
./ui/commands/auth_command.py
./ui/commands/base_command.py
./ui/commands/clear_command.py
./ui/commands/help_command.py
./ui/commands/memory_command.py
./ui/commands/placeholder_commands.py
./ui/commands/quit_command.py
./ui/commands/stats_command.py
./ui/utils/keyboard.py
./utils/__init__.py
./utils/base_content_generator.py
./utils/google_content_generator.py
./utils/llm_basics.py
./utils/llm_client.py
./utils/llm_config.py
./utils/openai_content_generator.py
./utils/qwen_content_generator.py
./utils/token_limits.py
./utils/tool_basics.py
pywen_agent-0.1.1.dist-info/METADATA
pywen_agent-0.1.1.dist-info/WHEEL
pywen_agent-0.1.1.dist-info/entry_points.txt
pywen_agent-0.1.1.dist-info/licenses/LICENSE
pywen_agent-0.1.1.dist-info/RECORD
